LICENSE
README.md
pyproject.toml
setup.py
doc2req/__init__.py
doc2req/util.py
doc2req.egg-info/PKG-INFO
doc2req.egg-info/SOURCES.txt
doc2req.egg-info/dependency_links.txt
doc2req.egg-info/requires.txt
doc2req.egg-info/top_level.txt
doc2req/etc/__init__.py
doc2req/etc/multi_model.py
doc2req/etc/unpackableObj.py
doc2req/model/__init__.py
doc2req/model/api.py
doc2req/model/example.py
doc2req/model/parameter.py
doc2req/model/point.py
doc2req/model/ret.py
doc2req/model/superset.py
doc2req/req/__init__.py
doc2req/req/handler.py
doc2req/req/hi.py
doc2req/req/prep.py
doc2req/req/result.py
doc2req/tool/__init__.py
doc2req/tool/parser.js