Metadata-Version: 2.1
Name: doc2req
Version: 0.9.0
Summary: apidoc to dataclasses and other useful utilities
Home-page: https://github.com/ZackaryW/doc2req
Author: Zackary W
Requires-Python: >=3.9
License-File: LICENSE
